[{
        "version": 3,
        "imageType": "SERVING",
        "processor": "CPU",
        "mlPackageLanguage": "PYTHON36_CV",
        "languageGroup": "CV",
        "baseImage": "python36cv:22.4.0-3",
        "runtimeImage": "",
        "displayName": "Python 36 CV"
},
{
        "version": 3,
        "imageType": "SERVING",
        "processor": "GPU",
        "mlPackageLanguage": "PYTHON36_CV",
        "languageGroup": "CV",
        "baseImage": "python36cv:22.4.0-3",
        "runtimeImage": "",
        "displayName": "Python 36 CV"
}]